dionysus/__init__.py
dionysus/__main__.py
dionysus/architectures.py
dionysus/constants.py
dionysus/loss.py
dionysus/training.py
dionysus/utils.py
dionysus_trainer-0.4.0.dist-info/LICENSE
dionysus_trainer-0.4.0.dist-info/METADATA
dionysus_trainer-0.4.0.dist-info/WHEEL
dionysus_trainer-0.4.0.dist-info/entry_points.txt
dionysus_trainer-0.4.0.dist-info/top_level.txt
dionysus_trainer-0.4.0.dist-info/RECORD
