Metadata-Version: 2.1
Name: dionysus-trainer
Version: 0.4.0
Summary: Training neural networks
Author-email: Felix Jobson <felix.jobson@outlook.de>
License: MIT License
Requires-Python: >=3.9
License-File: LICENSE
Requires-Dist: numpy >=1.23.2
Requires-Dist: pandas ==2.1.1
Requires-Dist: matplotlib ==3.7.1
Requires-Dist: seaborn ==0.12.2
Requires-Dist: scikit-learn ==1.2.2
Requires-Dist: torch ==2.1.0
Requires-Dist: tqdm ==4.65.0
Requires-Dist: requests ==2.31.0
Provides-Extra: dev
Requires-Dist: pytest ; extra == 'dev'
Requires-Dist: flake8 ; extra == 'dev'
